qr_connect/__init__.py
qr_connect/__main__.py
qr_connect/images/__init__.py
qr_connect/images/android.png
bb_qrconnectadb-0.0.2.dist-info/METADATA
bb_qrconnectadb-0.0.2.dist-info/WHEEL
bb_qrconnectadb-0.0.2.dist-info/RECORD
