Metadata-Version: 2.1
Name: bb-qrconnectadb
Version: 0.0.2
Summary: Connect to adb over wifi by scanning a QR code
Author: Erik Beebe
Author-email: beebeapps_debugging@tuta.io
Requires-Python: >=3.10,<4.0
Classifier: Programming Language :: Python :: 3
Classifier: Programming Language :: Python :: 3.10
Classifier: Programming Language :: Python :: 3.11
Requires-Dist: bb-apputils (>=0.3.7,<0.4.0)
Requires-Dist: pyqt6 (>=6.4.2,<7.0.0)
Requires-Dist: qrcode (>=7.4.2,<8.0.0)
Requires-Dist: sh (>=2.0.2,<3.0.0)
Requires-Dist: zeroconf (>=0.47.3,<0.48.0)
